realm_cli/__init__.py
realm_cli/compile_elm.py
realm_cli/main.py
realm_cli/p_assert.py
realm_cli/rust_json.py
realm_cli-0.0.5.dist-info/LICENSE
realm_cli-0.0.5.dist-info/METADATA
realm_cli-0.0.5.dist-info/WHEEL
realm_cli-0.0.5.dist-info/entry_points.txt
realm_cli-0.0.5.dist-info/top_level.txt
realm_cli-0.0.5.dist-info/RECORD
