Metadata-Version: 2.1
Name: realm-cli
Version: 0.0.5
Summary: A command line utitily to provide services offered by realm( a rust-elm web framework).
Home-page: https://github.com/ackotech/realm/
Author: nilinswap
Author-email: nilinswap@gmail.com
License: UNKNOWN
Platform: UNKNOWN
Requires-Dist: cookiecutter (>=1.6.0)
